fattureincloud/__init__.py
fattureincloud/base.py
fattureincloud/exceptions.py
fattureincloud/mixins.py
fattureincloud/utils.py
fattureincloud/objects/__init__.py
fattureincloud/objects/anagrafica/__init__.py
fattureincloud/objects/anagrafica/soggetto.py
fattureincloud/objects/documento/__init__.py
fattureincloud/objects/documento/fatture.py
fattureincloud-0.0.8.dist-info/LICENSE
fattureincloud-0.0.8.dist-info/METADATA
fattureincloud-0.0.8.dist-info/WHEEL
fattureincloud-0.0.8.dist-info/top_level.txt
fattureincloud-0.0.8.dist-info/RECORD
